balystic/__init__.py
balystic/models.py
balystic/urls.py
balystic/views.py
balystic/static/css/balystic.css
balystic/static/js/balystic.js
balystic/templates/balystic/base.html
django_balystic-0.1.0.dist-info/DESCRIPTION.rst
django_balystic-0.1.0.dist-info/METADATA
django_balystic-0.1.0.dist-info/RECORD
django_balystic-0.1.0.dist-info/WHEEL
django_balystic-0.1.0.dist-info/metadata.json
django_balystic-0.1.0.dist-info/top_level.txt
